[
  {
    "id": "BallSortPuzzle",
    "title": "Ball Sort Puzzle",
    "category": "Puzzle",
    "entry": "../BallSortPuzzle/index.html",
    "banner": "../arcade-hub/external-assets/ball-sort-puzzle-banner.png",
    "icon": "../arcade-hub/external-assets/local-icons/BallSortPuzzle.jpg",
    "orientation": "auto",
    "playMode": "iframe",
    "auditStatus": "正常"
  },
  {
    "id": "onet-fruit-classic",
    "title": "Onet Fruit Classic",
    "category": "Puzzle",
    "entry": "../onet-fruit-classic/index.html",
    "banner": "../arcade-hub/external-assets/onet-fruit-classic.png",
    "icon": "../arcade-hub/external-assets/local-icons/onet-fruit-classic.jpg",
    "orientation": "auto",
    "playMode": "iframe",
    "auditStatus": "正常"
  },
  {
    "id": "Amazing-bubble-breaker",
    "title": "Amazing Bubble Breaker",
    "category": "Arcade",
    "entry": "../Amazing-bubble-breaker/index.html",
    "banner": "../Amazing-bubble-breaker/assets/preloadbg.jpg",
    "icon": "../arcade-hub/external-assets/local-icons/Amazing-bubble-breaker.jpg",
    "orientation": "auto",
    "playMode": "iframe",
    "auditStatus": "正常"
  },
  {
    "id": "two-tiles",
    "title": "Two Tiles",
    "category": "Puzzle",
    "entry": "../two-tiles/index.html",
    "banner": "../two-tiles/images/block-sheet0.png",
    "icon": "../two-tiles/icons/icon-512.png",
    "orientation": "auto",
    "playMode": "iframe",
    "auditStatus": "正常"
  },
  {
    "id": "WaterSort",
    "title": "Water Sort",
    "category": "Puzzle",
    "entry": "../WaterSort/index.html",
    "banner": "../WaterSort/assets/textures/2x/default-resources.png",
    "icon": "../arcade-hub/external-assets/local-icons/WaterSort.jpg",
    "orientation": "auto",
    "playMode": "iframe",
    "auditStatus": "正常"
  },
  {
    "id": "CocktailSort",
    "title": "Cocktail Sort",
    "category": "Puzzle",
    "entry": "../CocktailSort/index.html",
    "banner": "../CocktailSort/assets/main/native/9d/9ddf1ae4-ff98-4bb0-a7c2-bb0ef7621ef6.png",
    "icon": "../arcade-hub/external-assets/local-icons/CocktailSort.jpg",
    "orientation": "auto",
    "playMode": "iframe",
    "auditStatus": "正常"
  },
  {
    "id": "BallSortMaster",
    "title": "Ball Sort Master",
    "category": "Puzzle",
    "entry": "../BallSortMaster/index.html",
    "banner": "../arcade-hub/external-assets/ball-sort-master.jpg",
    "icon": "../arcade-hub/external-assets/local-icons/BallSortMaster.jpg",
    "orientation": "portrait",
    "playMode": "iframe",
    "auditStatus": "需竖屏"
  },
  {
    "id": "One_Connect-main",
    "title": "One Connect",
    "category": "Puzzle",
    "entry": "../One_Connect-main/index.html",
    "banner": "../One_Connect-main/html5games/images/logo.png",
    "icon": "../One_Connect-main/icon.jpg",
    "orientation": "auto",
    "playMode": "iframe",
    "auditStatus": "正常"
  },
  {
    "id": "2048-cards",
    "title": "2048 Cards",
    "category": "Puzzle",
    "entry": "../2048-cards/index.html",
    "banner": null,
    "icon": "../2048-cards/icons/icon-512.png",
    "orientation": "auto",
    "playMode": "iframe",
    "auditStatus": "正常"
  },
  {
    "id": "2048-remastered",
    "title": "2048 Remastered",
    "category": "Puzzle",
    "entry": "../2048-remastered/v1.0.2/index.html",
    "banner": null,
    "icon": "../arcade-hub/external-assets/local-icons/2048-remastered.jpg",
    "orientation": "auto",
    "playMode": "iframe",
    "auditStatus": "正常"
  },
  {
    "id": "mahjong-classic",
    "title": "Mahjong Classic",
    "category": "Puzzle",
    "entry": "../mahjong-classic/index.html",
    "banner": null,
    "icon": "../mahjong-classic/icons/icon-512.png",
    "orientation": "auto",
    "playMode": "iframe",
    "auditStatus": "正常"
  },
  {
    "id": "happy-connect",
    "title": "Happy Connect",
    "category": "Puzzle",
    "entry": "../happy-connect/v1.0.0/index.html",
    "banner": null,
    "icon": "../arcade-hub/external-assets/local-icons/happy-connect.jpg",
    "orientation": "auto",
    "playMode": "iframe",
    "auditStatus": "正常"
  },
  {
    "id": "Christmas_Connect",
    "title": "Christmas Connect",
    "category": "Puzzle",
    "entry": "../Christmas_Connect/1/index.html",
    "banner": null,
    "icon": "../arcade-hub/external-assets/local-icons/Christmas_Connect.jpg",
    "orientation": "auto",
    "playMode": "iframe",
    "auditStatus": "正常"
  },
  {
    "id": "puzzle-color",
    "title": "Puzzle Color",
    "category": "Puzzle",
    "entry": "../puzzle-color/index.html",
    "banner": "../puzzle-color/images/tiledbackground-sheet0.png",
    "icon": "../puzzle-color/icons/icon-256.png",
    "orientation": "auto",
    "playMode": "iframe",
    "auditStatus": "正常"
  },
  {
    "id": "Find_Difference_2024",
    "title": "Find Difference 2024",
    "category": "Puzzle",
    "entry": "../Find_Difference_2024/index.html",
    "banner": "../Find_Difference_2024/splash.png",
    "icon": "../arcade-hub/external-assets/local-icons/Find_Difference_2024.jpg",
    "orientation": "portrait",
    "playMode": "iframe",
    "auditStatus": "需竖屏"
  },
  {
    "id": "Difference_Fun",
    "title": "Difference Fun",
    "category": "Puzzle",
    "entry": "../Difference_Fun/index.html",
    "banner": null,
    "icon": "../arcade-hub/external-assets/local-icons/Difference_Fun.jpg",
    "orientation": "auto",
    "playMode": "iframe",
    "auditStatus": "正常"
  },
  {
    "id": "Blocky",
    "title": "Blocky",
    "category": "Casual",
    "entry": "../Blocky/index.html",
    "banner": null,
    "icon": "../Blocky/icon-256.png",
    "orientation": "auto",
    "playMode": "iframe",
    "auditStatus": "正常"
  },
  {
    "id": "Slices",
    "title": "Slices",
    "category": "Casual",
    "entry": "../Slices/index.html",
    "banner": null,
    "icon": "../Slices/icon-256.png",
    "orientation": "auto",
    "playMode": "iframe",
    "auditStatus": "正常"
  },
  {
    "id": "HappyGlass",
    "title": "Happy Glass",
    "category": "Casual",
    "entry": "../HappyGlass/index.html",
    "banner": null,
    "icon": "../HappyGlass/icon-256.png",
    "orientation": "auto",
    "playMode": "iframe",
    "auditStatus": "正常"
  },
  {
    "id": "CandyBlast",
    "title": "Candy Blast",
    "category": "Casual",
    "entry": "../CandyBlast/index.html",
    "banner": "../CandyBlast/bg.png",
    "icon": "../arcade-hub/external-assets/local-icons/CandyBlast.jpg",
    "orientation": "auto",
    "playMode": "iframe",
    "auditStatus": "正常"
  },
  {
    "id": "house-paint",
    "title": "House Paint",
    "category": "Casual",
    "entry": "../house-paint/index.html",
    "banner": "../house-paint/images/tiledbackground-sheet0.png",
    "icon": "../house-paint/icons/icon-512.png",
    "orientation": "auto",
    "playMode": "iframe",
    "auditStatus": "正常"
  },
  {
    "id": "colored-bricks",
    "title": "Colored Bricks",
    "category": "Casual",
    "entry": "../colored-bricks/index.html",
    "banner": "../colored-bricks/images/tiledbackground-sheet0.png",
    "icon": "../colored-bricks/icons/icon-512.png",
    "orientation": "auto",
    "playMode": "iframe",
    "auditStatus": "正常"
  },
  {
    "id": "Node",
    "title": "Node",
    "category": "Casual",
    "entry": "../Node/index.html",
    "banner": "../Node/images/homebackground-sheet0.png",
    "icon": "../Node/icon-256.png",
    "orientation": "auto",
    "playMode": "iframe",
    "auditStatus": "正常"
  },
  {
    "id": "Release",
    "title": "Release",
    "category": "Casual",
    "entry": "../Release/index.html",
    "banner": "../Release/images/target.png",
    "icon": "../Release/icon-256.png",
    "orientation": "auto",
    "playMode": "iframe",
    "auditStatus": "正常"
  },
  {
    "id": "SquArea",
    "title": "Squ Area",
    "category": "Casual",
    "entry": "../SquArea/index.html",
    "banner": "../SquArea/images/lfbackground-sheet0.png",
    "icon": "../SquArea/icon-256.png",
    "orientation": "auto",
    "playMode": "iframe",
    "auditStatus": "正常"
  },
  {
    "id": "sorting-balls",
    "title": "Sorting Balls",
    "category": "Casual",
    "entry": "../sorting-balls/index.html",
    "banner": "../sorting-balls/images/tiledbackground-sheet0.png",
    "icon": "../sorting-balls/icons/icon-512.png",
    "orientation": "auto",
    "playMode": "iframe",
    "auditStatus": "正常"
  },
  {
    "id": "The_Pets_Rush",
    "title": "The Pets Rush",
    "category": "Casual",
    "entry": "../The_Pets_Rush/index.html",
    "banner": "../The_Pets_Rush/images/tiledbackground-sheet0.png",
    "icon": "../arcade-hub/external-assets/local-icons/The_Pets_Rush.jpg",
    "orientation": "auto",
    "playMode": "iframe",
    "auditStatus": "正常"
  },
  {
    "id": "TakeOff",
    "title": "Take Off",
    "category": "Casual",
    "entry": "../TakeOff/index.html",
    "banner": "../TakeOff/images/gamehelixcover-sheet0.png",
    "icon": "../TakeOff/icon-256.png",
    "orientation": "auto",
    "playMode": "iframe",
    "auditStatus": "正常"
  },
  {
    "id": "Basketball_REAL",
    "title": "Basketball REAL",
    "category": "Casual",
    "entry": "../Basketball_REAL/index.html",
    "banner": "../Basketball_REAL/images/cs2.jpg",
    "icon": "../arcade-hub/external-assets/local-icons/Basketball_REAL.jpg",
    "orientation": "auto",
    "playMode": "iframe",
    "auditStatus": "正常"
  },
  {
    "id": "Magic_Tiles3_Online_Z",
    "title": "Magic Tiles3 Online Z",
    "category": "Casual",
    "entry": "../Magic_Tiles3_Online_Z/index.html",
    "banner": "../Magic_Tiles3_Online_Z/resource/assets/Slider/thumb.png",
    "icon": "../arcade-hub/external-assets/local-icons/Magic_Tiles3_Online_Z.jpg",
    "orientation": "portrait",
    "playMode": "iframe",
    "auditStatus": "需竖屏"
  },
  {
    "id": "PianoTitle",
    "title": "Piano Title",
    "category": "Casual",
    "entry": "../PianoTitle/index.html",
    "banner": "../PianoTitle/splash.png",
    "icon": "../arcade-hub/external-assets/local-icons/PianoTitle.jpg",
    "orientation": "portrait",
    "playMode": "iframe",
    "auditStatus": "需竖屏"
  },
  {
    "id": "jelly-merger",
    "title": "Jelly Merger",
    "category": "Casual",
    "entry": "../jelly-merger/index.html",
    "banner": null,
    "icon": "../jelly-merger/icon-256.png",
    "orientation": "auto",
    "playMode": "iframe",
    "auditStatus": "正常"
  },
  {
    "id": "FlappyShooter",
    "title": "Flappy Shooter",
    "category": "Action",
    "entry": "../FlappyShooter/index.html",
    "banner": null,
    "icon": "../FlappyShooter/icon-256.png",
    "orientation": "auto",
    "playMode": "iframe",
    "auditStatus": "正常"
  },
  {
    "id": "DrawTheDefense",
    "title": "Draw The Defense",
    "category": "Action",
    "entry": "../DrawTheDefense/index.html",
    "banner": "../DrawTheDefense/Images/splash.png",
    "icon": "../arcade-hub/external-assets/local-icons/DrawTheDefense.jpg",
    "orientation": "auto",
    "playMode": "iframe",
    "auditStatus": "正常"
  },
  {
    "id": "alien-attack",
    "title": "Alien Attack",
    "category": "Action",
    "entry": "../alien-attack/v010/index.html",
    "banner": "../alien-attack/v010/assets/background.jpg",
    "icon": "../arcade-hub/external-assets/local-icons/alien_attack.jpg",
    "orientation": "auto",
    "playMode": "iframe",
    "auditStatus": "正常"
  },
  {
    "id": "mr-gun",
    "title": "Mr Gun",
    "category": "Action",
    "entry": "../mr-gun/index.html",
    "banner": null,
    "icon": "../mr-gun/icons/icon-512.png",
    "orientation": "auto",
    "playMode": "iframe",
    "auditStatus": "正常"
  },
  {
    "id": "flip-the-gun",
    "title": "Flip The Gun",
    "category": "Action",
    "entry": "../flip-the-gun/index.html",
    "banner": null,
    "icon": "../flip-the-gun/icon-256.png",
    "orientation": "auto",
    "playMode": "iframe",
    "auditStatus": "正常"
  },
  {
    "id": "Space_Shooter",
    "title": "Space Shooter",
    "category": "Action",
    "entry": "../Space_Shooter/index.html",
    "banner": "../Space_Shooter/splash.png",
    "icon": "../Space_Shooter/a9eab1395a0c51d8be2e16d1326c91e7_icon.png",
    "orientation": "auto",
    "playMode": "iframe",
    "auditStatus": "正常"
  },
  {
    "id": "Meteorite_Shooter",
    "title": "Meteorite Shooter",
    "category": "Action",
    "entry": "../Meteorite_Shooter/index.html",
    "banner": "../Meteorite_Shooter/splash.png",
    "icon": "../arcade-hub/external-assets/local-icons/Meteorite_Shooter.jpg",
    "orientation": "portrait",
    "playMode": "iframe",
    "auditStatus": "需竖屏"
  },
  {
    "id": "Merge_Gun_Elite_Shooting",
    "title": "Merge Gun Elite Shooting",
    "category": "Action",
    "entry": "../Merge_Gun_Elite_Shooting/index.html",
    "banner": "../Merge_Gun_Elite_Shooting/_base/banner.jpg",
    "icon": "../arcade-hub/external-assets/local-icons/Merge_Gun_Elite_Shooting.jpg",
    "orientation": "landscape",
    "playMode": "iframe",
    "auditStatus": "正常"
  },
  {
    "id": "MoveTheCar",
    "title": "Move The Car",
    "category": "Racing",
    "entry": "../MoveTheCar/game/index.html",
    "banner": null,
    "icon": "../arcade-hub/external-assets/local-icons/MoveTheCar.jpg",
    "orientation": "auto",
    "playMode": "iframe",
    "auditStatus": "正常"
  },
  {
    "id": "parking-way",
    "title": "Parking Way",
    "category": "Racing",
    "entry": "../parking-way/v1.0.55/index.html",
    "banner": "../parking-way/v1.0.55/images/tiledbackground-sheet0.webp",
    "icon": "../arcade-hub/external-assets/local-icons/parking-way.jpg",
    "orientation": "auto",
    "playMode": "iframe",
    "auditStatus": "正常"
  },
  {
    "id": "crazy_parking",
    "title": "Crazy Parking",
    "category": "Racing",
    "entry": "../crazy_parking/index.html",
    "banner": null,
    "icon": "../arcade-hub/external-assets/local-icons/crazy_parking.jpg",
    "orientation": "auto",
    "playMode": "iframe",
    "auditStatus": "正常"
  },
  {
    "id": "taxi-pick-up",
    "title": "Taxi Pick Up",
    "category": "Racing",
    "entry": "../taxi-pick-up/index.html",
    "banner": "../taxi-pick-up/images/tiledbackground-sheet0.png",
    "icon": "../taxi-pick-up/icons/icon-256.png",
    "orientation": "auto",
    "playMode": "iframe",
    "auditStatus": "正常"
  },
  {
    "id": "Parking_Fury",
    "title": "Parking Fury",
    "category": "Racing",
    "entry": "../Parking_Fury/index.html",
    "banner": "../Parking_Fury/assets/background_menu.png",
    "icon": "../arcade-hub/external-assets/local-icons/Parking_Fury.jpg",
    "orientation": "auto",
    "playMode": "iframe",
    "auditStatus": "正常"
  },
  {
    "id": "ParkingOut",
    "title": "Parking Out",
    "category": "Racing",
    "entry": "../ParkingOut/glgame/index.html",
    "banner": "../ParkingOut/glgame/background.jpg",
    "icon": "../arcade-hub/external-assets/local-icons/ParkingOut.jpg",
    "orientation": "auto",
    "playMode": "iframe",
    "auditStatus": "正常"
  },
  {
    "id": "tap-tap-dunk",
    "title": "Tap Tap Dunk",
    "category": "Sports",
    "entry": "../tap-tap-dunk/index.html",
    "banner": "../tap-tap-dunk/html5games/branding/default/More_Games600x253_transparent.png",
    "icon": "../tap-tap-dunk/portal/html5games/images/tmp/TapTapDunkTeaser.jpg",
    "orientation": "auto",
    "playMode": "iframe",
    "auditStatus": "正常"
  },
  {
    "id": "dunk-shot",
    "title": "Dunk Shot",
    "category": "Sports",
    "entry": "../dunk-shot/index.html",
    "banner": "../dunk-shot/images/txtbestscore.png",
    "icon": "../dunk-shot/icon-256.png",
    "orientation": "auto",
    "playMode": "iframe",
    "auditStatus": "正常"
  },
  {
    "id": "basket-slide",
    "title": "Basket Slide",
    "category": "Sports",
    "entry": "../basket-slide/index.html",
    "banner": "../basket-slide/images/tiledbackground-sheet0.png",
    "icon": "../basket-slide/icons/icon-512.png",
    "orientation": "auto",
    "playMode": "iframe",
    "auditStatus": "正常"
  },
  {
    "id": "mini-golf",
    "title": "Mini Golf",
    "category": "Sports",
    "entry": "../mini-golf/index.html",
    "banner": null,
    "icon": "../mini-golf/icon-256.png",
    "orientation": "auto",
    "playMode": "iframe",
    "auditStatus": "正常"
  },
  {
    "id": "american-football-challenge",
    "title": "American Football Challenge",
    "category": "Sports",
    "entry": "../american-football-challenge/index.html",
    "banner": null,
    "icon": "../american-football-challenge/icons/icon-512.png",
    "orientation": "auto",
    "playMode": "iframe",
    "auditStatus": "正常"
  },
  {
    "id": "DunkLine",
    "title": "Dunk Line",
    "category": "Sports",
    "entry": "../DunkLine/index.html",
    "banner": null,
    "icon": "../DunkLine/icons/icon-512.png",
    "orientation": "auto",
    "playMode": "iframe",
    "auditStatus": "正常"
  },
  {
    "id": "rolly-vortex",
    "title": "Rolly Vortex",
    "category": "Arcade",
    "entry": "../rolly-vortex/index.html",
    "banner": "../rolly-vortex/images/txtscore.png",
    "icon": "../rolly-vortex/icon-256.png",
    "orientation": "auto",
    "playMode": "iframe",
    "auditStatus": "正常"
  },
  {
    "id": "knife-hit",
    "title": "Knife Hit",
    "category": "Arcade",
    "entry": "../knife-hit/index.html",
    "banner": null,
    "icon": "../knife-hit/icons/icon-256.png",
    "orientation": "auto",
    "playMode": "iframe",
    "auditStatus": "正常"
  },
  {
    "id": "color-tunnel",
    "title": "Color Tunnel",
    "category": "Arcade",
    "entry": "../color-tunnel/index.html",
    "banner": "../color-tunnel/html5games/branding/default/More_Games600x253_transparent.png",
    "icon": "../color-tunnel/files/assets/79039612/1/ui_icon_pause.png",
    "orientation": "auto",
    "playMode": "iframe",
    "auditStatus": "正常"
  },
  {
    "id": "neon-tower",
    "title": "Neon Tower",
    "category": "Arcade",
    "entry": "../neon-tower/index.html",
    "banner": "../neon-tower/html5games/branding/default/More_Games600x253_transparent.png",
    "icon": "../neon-tower/portal/html5games/images/tmp/NeonTowerTeaser.jpg",
    "orientation": "auto",
    "playMode": "iframe",
    "auditStatus": "正常"
  },
  {
    "id": "neon-swing",
    "title": "Neon Swing",
    "category": "Arcade",
    "entry": "../neon-swing/index.html",
    "banner": "../neon-swing/html5games/branding/default/More_Games600x253_transparent.png",
    "icon": "../neon-swing/portal/html5games/images/tmp/180/NeonSwingTeaser.jpg",
    "orientation": "auto",
    "playMode": "iframe",
    "auditStatus": "正常"
  },
  {
    "id": "FruitMaster",
    "title": "Fruit Master",
    "category": "Arcade",
    "entry": "../FruitMaster/index.html",
    "banner": "../FruitMaster/images/splash3.png",
    "icon": "../arcade-hub/external-assets/local-icons/FruitMaster.jpg",
    "orientation": "auto",
    "playMode": "iframe",
    "auditStatus": "正常"
  },
  {
    "id": "CubeJump",
    "title": "Cube Jump",
    "category": "Arcade",
    "entry": "../CubeJump/index.html",
    "banner": null,
    "icon": "../CubeJump/icon-256.png",
    "orientation": "auto",
    "playMode": "iframe",
    "auditStatus": "正常"
  },
  {
    "id": "SubwaySurfers_vegas",
    "title": "Subway Surfers Vegas",
    "category": "Racing",
    "entry": "../SubwaySurfers_vegas/index.html",
    "banner": "../SubwaySurfers_vegas/assets/preload/splash.png",
    "icon": "../arcade-hub/external-assets/local-icons/SubwaySurfers_vegas.jpg",
    "orientation": "auto",
    "playMode": "iframe",
    "auditStatus": "正常"
  },
  {
    "id": "Basketball_Crazy",
    "title": "Basketball Crazy",
    "category": "Casual",
    "entry": "../Basketball_Crazy/index.html",
    "banner": "../Basketball_Crazy/res/native/imgLoading.jpg",
    "icon": "../arcade-hub/external-assets/local-icons/Basketball_Crazy.jpg",
    "orientation": "landscape",
    "playMode": "iframe",
    "auditStatus": "正常"
  },
  {
    "id": "Onet_Link",
    "title": "Onet Link",
    "category": "Puzzle",
    "entry": "../Onet_Link/index.html",
    "banner": "../arcade-hub/external-assets/onet-link-banner.webp",
    "icon": "../arcade-hub/external-assets/local-icons/Onet_Link.jpg",
    "orientation": "portrait",
    "playMode": "iframe",
    "auditStatus": "需竖屏"
  }
]